EasyMCP2221/Constants.py
EasyMCP2221/I2C_Slave.py
EasyMCP2221/MCP2221.py
EasyMCP2221/__init__.py
EasyMCP2221/exceptions.py
EasyMCP2221/smbus.py
easymcp2221-1.8.2.dist-info/LICENSE
easymcp2221-1.8.2.dist-info/WHEEL
easymcp2221-1.8.2.dist-info/METADATA
easymcp2221-1.8.2.dist-info/RECORD
