Metadata-Version: 2.3
Name: EasyMCP2221
Version: 1.8.2
Summary: Python module to interface with MCP2221 focused on ease of use.
Author-email: Reinoso Guzman <electronicayciencia@gmail.com>
Requires-Python: >=3.6
Classifier: Programming Language :: Python :: 3
Classifier: License :: OSI Approved :: MIT License
Classifier: Operating System :: OS Independent
Requires-Dist: hidapi
Project-URL: Bug Tracker, https://github.com/electronicayciencia/EasyMCP2221/issues
Project-URL: Documentation, https://easymcp2221.readthedocs.io/
Project-URL: Homepage, https://github.com/electronicayciencia/EasyMCP2221
